neuralnetlib/__init__.py
neuralnetlib/activations.py
neuralnetlib/callbacks.py
neuralnetlib/layers.py
neuralnetlib/learners.py
neuralnetlib/losses.py
neuralnetlib/metrics.py
neuralnetlib/models.py
neuralnetlib/optimizers.py
neuralnetlib/preprocessing.py
neuralnetlib/regularizers.py
neuralnetlib/utils.py
neuralnetlib-4.4.0.dist-info/LICENSE
neuralnetlib-4.4.0.dist-info/METADATA
neuralnetlib-4.4.0.dist-info/WHEEL
neuralnetlib-4.4.0.dist-info/top_level.txt
neuralnetlib-4.4.0.dist-info/RECORD
